satelite/__init__.py
satelite/config.py
satelite/core/__init__.py
satelite/core/downloader.py
satelite/core/uploader.py
satelite/gdal/__init__.py
satelite/gdal/gdal_commands.py
satelite/models/__init__.py
satelite/models/s2_enum.py
satelite/raster/__init__.py
satelite/raster/raster.py
satelite/sentinel2/__init__.py
satelite/sentinel2/fetch_unique_tile_date.py
satelite/sentinel2/fetch_unique_tile_date_pystac.py
satelite/sentinel2/get_tiles.py
satelite/sentinel2/mosaic_custom_bands.py
satelite/sentinel2/mosaic_same_bands.py
satelite/sentinel2/path_row_from_shp.py
satelite/sentinel2/s2_l1c_urls.py
satelite/sentinel2/s2_l2a_urls.py
satelite/sentinel2/band_stack/__init__.py
satelite/sentinel2/band_stack/generate_band_stack.py
satelite/sentinel2/indices/__init__.py
satelite/sentinel2/indices/general_indices.py
satelite/tests/__init__.py
satelite/tests/conftest.py
satelite/tests/sentinel2/__init__.py
satelite/tests/sentinel2/test_fetch_unique_tile_date.py
satelite/tests/sentinel2/test_fetch_unique_tile_date_pystac.py
satelite/tests/sentinel2/test_genarate_band_stack.py
satelite/tests/sentinel2/test_general_indices.py
satelite/tests/sentinel2/test_get_tile.py
satelite/tests/sentinel2/test_mosaic_same_bands.py
satelite/tests/sentinel2/test_s2_l1c_urls.py
satelite/tests/sentinel2/test_s2_l2a_urls.py
satelite/tests/sentinel2/test_validate.py
satelite/validators/__init__.py
satelite/validators/check_shape_of_rid.py
satsure_core/__init__.py
satsure_core/satelite/__init__.py
satsure_core/satelite/config.py
satsure_core/satelite/core/__init__.py
satsure_core/satelite/core/downloader.py
satsure_core/satelite/core/extraction.py
satsure_core/satelite/core/uploader.py
satsure_core/satelite/gdal/__init__.py
satsure_core/satelite/gdal/_extents.py
satsure_core/satelite/gdal/_projection.py
satsure_core/satelite/gdal/_raster_ops.py
satsure_core/satelite/gdal/_resolution.py
satsure_core/satelite/models/__init__.py
satsure_core/satelite/models/s2_enum.py
satsure_core_test-0.3.6.dist-info/LICENCE.txt
satsure_core_test-0.3.6.dist-info/METADATA
satsure_core_test-0.3.6.dist-info/WHEEL
satsure_core_test-0.3.6.dist-info/top_level.txt
satsure_core_test-0.3.6.dist-info/RECORD
