Metadata-Version: 2.1
Name: satsure-core-test
Version: 0.3.6
Summary: satsure core package
Author: Satsure
Author-email: kmstpm@email.com
License-File: LICENCE.txt
Requires-Dist: awscli
Requires-Dist: boto3
Requires-Dist: fiona
Requires-Dist: gdal ==3.6.2
Requires-Dist: google-cloud-storage
Requires-Dist: pandas
Requires-Dist: pyproj
Requires-Dist: pystac
Requires-Dist: pystac-client
Requires-Dist: python-dotenv
Requires-Dist: rasterstats
Requires-Dist: rasterio
Requires-Dist: requests
Requires-Dist: sqlalchemy
Requires-Dist: wget
